tixent/__init__.py
tixent/_core.py
tixent/exceptions.py
tixent/py.typed
tixent/types.py
tixent-0.0.3.dist-info/METADATA
tixent-0.0.3.dist-info/WHEEL
tixent-0.0.3.dist-info/licenses/LICENSE
tixent-0.0.3.dist-info/RECORD
