Metadata-Version: 2.1
Name: tixent
Version: 0.0.3
Summary: A text splitting tool
Project-URL: Documentation, https://github.com/sincekmori/tixent#readme
Project-URL: Issues, https://github.com/sincekmori/tixent/issues
Project-URL: Source, https://github.com/sincekmori/tixent
Author-email: Shinsuke Mori <sincekmori@gmail.com>
License-Expression: MIT
License-File: LICENSE
Keywords: openai,tiktoken,token
Classifier: Development Status :: 4 - Beta
Classifier: Intended Audience :: Developers
Classifier: License :: OSI Approved :: MIT License
Classifier: Operating System :: OS Independent
Classifier: Programming Language :: Python
Classifier: Programming Language :: Python :: 3 :: Only
Classifier: Programming Language :: Python :: 3.8
Classifier: Programming Language :: Python :: 3.9
Classifier: Programming Language :: Python :: 3.10
Classifier: Programming Language :: Python :: 3.11
Classifier: Programming Language :: Python :: Implementation :: CPython
Requires-Python: >=3.8
Requires-Dist: tiktoken>=0.4.0
